regfex/__init__.py
regfex/main.py
regfex-1.0.3.dist-info/LICENSE
regfex-1.0.3.dist-info/METADATA
regfex-1.0.3.dist-info/WHEEL
regfex-1.0.3.dist-info/top_level.txt
regfex-1.0.3.dist-info/RECORD
