Metadata-Version: 2.1
Name: regfex
Version: 1.0.3
Summary: Get regular expressions from .re files!
Home-page: https://github.com/woidzero/regfex
Author: woidzero
Author-email: woidzeroo@gmail.com
License: MIT License
License-File: LICENSE
